<?xml version="1.0" encoding="UTF-8"?>
<recordTypeHaul xmlns:a="http://www.appian.com/ae/types/2009" xmlns:xsi="http://www.w3.org/2001/XMLSchema-instance">
  <versionUuid>68fcfc5d-db09-452e-8408-db9e47cd901c</versionUuid>
  <recordType a:uuid="7c79ac0c-da15-4288-a93e-0e54d0650a34" name="PS Inmate Subscriber">
    <a:pluralName>PS Inmate Subscribers</a:pluralName>
    <a:description>Users subscribed to conversations on Inmate events in an event history list component</a:description>
    <a:urlStub>uTjPGw</a:urlStub>
    <a:source xsi:type="a:RecordsReplica"/>
    <a:listViewTemplateExpr>#"SYSTEM_SYSRULES_recordGridField"(
    columns: {
        #"SYSTEM_SYSRULES_gridColumn"(
          label: "Id",
          sortField: #"urn:appian:record-field:v1:7c79ac0c-da15-4288-a93e-0e54d0650a34/0559923a-e76e-4e45-acf7-8dd9590b7168",
          value: fv!row[#"urn:appian:record-field:v1:7c79ac0c-da15-4288-a93e-0e54d0650a34/0559923a-e76e-4e45-acf7-8dd9590b7168"],
          align: "END"
        ),
        #"SYSTEM_SYSRULES_gridColumn"(
          label: "inmate",
          sortField: #"urn:appian:record-field:v1:7c79ac0c-da15-4288-a93e-0e54d0650a34/1cccb9af-de69-4992-9baf-644156555543/d70d7a0c-0ee6-4949-84d6-2c58d8caffcc",
          value: #"SYSTEM_SYSRULES_linkField"(
            links: {
              #"SYSTEM_SYSRULES_recordLink"(
                label: fv!row[#"urn:appian:record-field:v1:7c79ac0c-da15-4288-a93e-0e54d0650a34/1cccb9af-de69-4992-9baf-644156555543/d70d7a0c-0ee6-4949-84d6-2c58d8caffcc"],
                recordType: #"urn:appian:record-type:v1:7c79ac0c-da15-4288-a93e-0e54d0650a34",
                identifier: fv!identifier
              )
            }
          ),
          align: "END"
        ),
        #"SYSTEM_SYSRULES_gridColumn"(
          label: "subscriberUser",
          sortField: #"urn:appian:record-field:v1:7c79ac0c-da15-4288-a93e-0e54d0650a34/cbbfb54d-7aeb-48e4-823f-d47560e1cbb3/SYSTEM_RECORD_TYPE_USER_FIELD_username",
          value: fv!row[#"urn:appian:record-field:v1:7c79ac0c-da15-4288-a93e-0e54d0650a34/cbbfb54d-7aeb-48e4-823f-d47560e1cbb3/SYSTEM_RECORD_TYPE_USER_FIELD_username"]
        )
      },
      pageSize: 50,
      shadeAlternateRows: true
    )</a:listViewTemplateExpr>
    <a:detailViewCfg>
      <a:nameExpr>#"SYSTEM_SYSRULES_rtd_getDefaultSummaryViewName"()</a:nameExpr>
      <a:uiExpr/>
      <a:visibilityExpr>=true()</a:visibilityExpr>
      <a:urlStub>summary</a:urlStub>
      <a:headerExpr/>
      <a:recordActionLaunchType>DIALOG</a:recordActionLaunchType>
      <a:recordUiSecurityType>EXPRESSION</a:recordUiSecurityType>
    </a:detailViewCfg>
    <a:isSystem>false</a:isSystem>
    <a:dataSrcExpr/>
    <a:facetsListExpr/>
    <a:titleExpr>rv!record[#"urn:appian:record-field:v1:7c79ac0c-da15-4288-a93e-0e54d0650a34/0559923a-e76e-4e45-acf7-8dd9590b7168"]</a:titleExpr>
    <a:defaultFiltersExpr/>
    <a:layoutType>GRID</a:layoutType>
    <a:security>16383</a:security>
    <a:hideLatestNews>false</a:hideLatestNews>
    <a:hideNewsView>false</a:hideNewsView>
    <a:hideRelatedActionsView>false</a:hideRelatedActionsView>
    <a:isExportable>true</a:isExportable>
    <a:listViewSrcExpr/>
    <a:recordViewSrcExpr/>
    <a:recordRelationshipCfg>
      <uuid>1cccb9af-de69-4992-9baf-644156555543</uuid>
      <relationshipName>inmate</relationshipName>
      <targetRecordTypeUuid>b9f2b8a1-aa3c-420e-9856-a362e5c58683</targetRecordTypeUuid>
      <relationshipType>MANY_TO_ONE</relationshipType>
      <relationshipData>{"sourceRecordTypeFieldUuid":"8e6b3a6e-a42d-4d04-a0e8-06e214777638","targetRecordTypeFieldUuid":"d70d7a0c-0ee6-4949-84d6-2c58d8caffcc","relationshipOperator":"1","joinTableSourceField":"","joinTableTargetField":""}</relationshipData>
      <updateBehavior>NON_CASCADING</updateBehavior>
    </a:recordRelationshipCfg>
    <a:recordRelationshipCfg>
      <uuid>cbbfb54d-7aeb-48e4-823f-d47560e1cbb3</uuid>
      <relationshipName>subscriberUser</relationshipName>
      <targetRecordTypeUuid>SYSTEM_RECORD_TYPE_USER</targetRecordTypeUuid>
      <relationshipType>MANY_TO_ONE</relationshipType>
      <relationshipData>{"sourceRecordTypeFieldUuid":"ec6f4c96-a02e-4e2e-a519-45cd5fd063b1","targetRecordTypeFieldUuid":"SYSTEM_RECORD_TYPE_USER_FIELD_username","relationshipOperator":"1","joinTableSourceField":"","joinTableTargetField":""}</relationshipData>
      <updateBehavior>NON_CASCADING</updateBehavior>
    </a:recordRelationshipCfg>
    <a:recordTypeSearchCfg>
      <searchFieldsSrc>DEFAULT</searchFieldsSrc>
      <placeholderSrc>DEFAULT</placeholderSrc>
      <placeholder/>
    </a:recordTypeSearchCfg>
    <a:iconId/>
    <a:listAutoRefreshInterval>0.0</a:listAutoRefreshInterval>
    <a:sourceConfiguration>
      <sourceUuid>PS_INMATE_SUBSCRIBER@_a-0000ee0e-a4b3-8000-9bf2-011c48011c48_1642755</sourceUuid>
      <sourceType>RDBMS_TABLE</sourceType>
      <sourceSubType>NONE</sourceSubType>
      <sourceContextExpr/>
      <friendlyName>PS_INMATE_SUBSCRIBER</friendlyName>
      <sourceFilterExpr/>
      <field>
        <uuid>0559923a-e76e-4e45-acf7-8dd9590b7168</uuid>
        <type>{http://www.appian.com/ae/types/2009}Integer</type>
        <sourceFieldName>ID</sourceFieldName>
        <sourceFieldType>INTEGER</sourceFieldType>
        <fieldName>id</fieldName>
        <displayName>Id</displayName>
        <isRecordId>true</isRecordId>
        <isUnique>true</isUnique>
        <isCustomField>false</isCustomField>
        <customFieldExpr/>
        <customFieldDefaultValueStr>null</customFieldDefaultValueStr>
        <fieldCalculationType>NA</fieldCalculationType>
        <fieldTemplateType>NA</fieldTemplateType>
        <recordFieldSecurityMembershipFilter/>
        <fieldFormat/>
        <isIndexable>false</isIndexable>
        <subType>NA</subType>
      </field>
      <field>
        <uuid>8e6b3a6e-a42d-4d04-a0e8-06e214777638</uuid>
        <type>{http://www.appian.com/ae/types/2009}Integer</type>
        <sourceFieldName>RECORD_ID</sourceFieldName>
        <sourceFieldType>INTEGER</sourceFieldType>
        <fieldName>recordId</fieldName>
        <displayName>Record Id</displayName>
        <isRecordId>false</isRecordId>
        <isUnique>false</isUnique>
        <isCustomField>false</isCustomField>
        <customFieldExpr/>
        <customFieldDefaultValueStr>null</customFieldDefaultValueStr>
        <fieldCalculationType>NA</fieldCalculationType>
        <fieldTemplateType>NA</fieldTemplateType>
        <recordFieldSecurityMembershipFilter/>
        <fieldFormat/>
        <isIndexable>false</isIndexable>
        <subType>NA</subType>
      </field>
      <field>
        <uuid>ec6f4c96-a02e-4e2e-a519-45cd5fd063b1</uuid>
        <type>{http://www.appian.com/ae/types/2009}User</type>
        <sourceFieldName>USER</sourceFieldName>
        <sourceFieldType>VARCHAR(255)</sourceFieldType>
        <fieldName>user</fieldName>
        <displayName>User</displayName>
        <isRecordId>false</isRecordId>
        <isUnique>false</isUnique>
        <isCustomField>false</isCustomField>
        <customFieldExpr/>
        <customFieldDefaultValueStr>null</customFieldDefaultValueStr>
        <fieldCalculationType>NA</fieldCalculationType>
        <fieldTemplateType>NA</fieldTemplateType>
        <recordFieldSecurityMembershipFilter/>
        <fieldFormat/>
        <isIndexable>false</isIndexable>
        <subType>NA</subType>
      </field>
      <uuid>0ee0862a-0f96-40ba-bf1e-02c8f4b1e4f8</uuid>
      <refreshSchedule>
        <frequency>DAILY</frequency>
        <value>{"hour":3,"minute":"00","amPM":"AM","timeZone":"Europe/Berlin","version":"v1"}</value>
        <activated>false</activated>
      </refreshSchedule>
      <skipFailureEnabled>true</skipFailureEnabled>
      <recordIdGeneratorUuid/>
    </a:sourceConfiguration>
    <a:enabledFeatures>511</a:enabledFeatures>
    <a:isVisibleInRecordTypeList>false</a:isVisibleInRecordTypeList>
    <a:recordActionLaunchType>DIALOG</a:recordActionLaunchType>
    <a:showSearchBox>true</a:showSearchBox>
    <a:isVisibleInDataFabric>false</a:isVisibleInDataFabric>
    <a:usesRollingSyncLimit>false</a:usesRollingSyncLimit>
    <a:usesRecoverySync>false</a:usesRecoverySync>
    <a:isScheduledIndexingEnabled>false</a:isScheduledIndexingEnabled>
  </recordType>
  <roleMap>
    <role name="record_type_administrator">
      <users/>
      <groups>
        <groupUuid>_e-0000ed02-f61f-8000-9b37-01075c01075c_5585</groupUuid>
      </groups>
    </role>
    <role name="record_type_viewer">
      <users/>
      <groups>
        <groupUuid>_e-0000ed02-f61f-8000-9b37-01075c01075c_5587</groupUuid>
      </groups>
    </role>
  </roleMap>
  <history>
    <historyInfo versionUuid="7c79ac0c-da15-4288-a93e-0e54d0650a34"/>
    <historyInfo versionUuid="68fcfc5d-db09-452e-8408-db9e47cd901c"/>
  </history>
  <migrationVersion>1</migrationVersion>
</recordTypeHaul>
