<?xml version="1.0" encoding="UTF-8"?>
<processModelHaul>
  <versionUuid>0001ee4d-47e0-8000-8a0f-109188109188</versionUuid>
  <folderUuid>5b8e539e-8b2a-41df-b195-d482a1b1c6ef</folderUuid>
  <roleMap>
    <role name="ADMIN_OWNER">
      <users/>
      <groups>
        <groupUuid>_e-0000ed87-210d-8000-9b3b-01075c01075c_6563</groupUuid>
      </groups>
    </role>
    <role name="EDITOR">
      <users/>
      <groups/>
    </role>
    <role name="EXPLICIT_NONMEMBER">
      <users/>
      <groups/>
    </role>
    <role name="VIEWER">
      <users/>
      <groups>
        <groupUuid>_e-0000ed87-210d-8000-9b3b-01075c01075c_6561</groupUuid>
      </groups>
    </role>
    <role name="MANAGER">
      <users/>
      <groups/>
    </role>
    <role name="INITIATOR">
      <users/>
      <groups/>
    </role>
  </roleMap>
  <process_model_port schemaVersion="007.000.004"
    xmlns="http://www.appian.com/ae/types/2009"
    xmlns:a="http://www.appian.com/ae/types/2009"
    xmlns:xsd="http://www.w3.org/2001/XMLSchema" xmlns:xsi="http://www.w3.org/2001/XMLSchema-instance">
    <pm>
      <meta>
        <uuid><![CDATA[0002ee0c-e41d-8000-270c-7f0000014e7a]]></uuid>
        <name>
          <string-map>
            <pair>
              <locale country="" lang="de" variant=""/>
              <value><![CDATA[PS Fill Out Event Opinion]]></value>
            </pair>
            <pair>
              <locale country="US" lang="en" variant=""/>
              <value><![CDATA[PS Fill Out Event Opinion]]></value>
            </pair>
          </string-map>
        </name>
        <desc>
          <string-map>
            <pair>
              <locale country="" lang="de" variant=""/>
              <value/>
            </pair>
            <pair>
              <locale country="US" lang="en" variant=""/>
              <value/>
            </pair>
          </string-map>
        </desc>
        <versionStatus>2</versionStatus>
        <process-name>
          <string-map>
            <pair>
              <locale country="" lang="de" variant=""/>
              <value><![CDATA[=#"urn:appian:translation-string:v1:1ef8ea71-d1f4-4e54-909c-ab2083f30c0b"]]></value>
            </pair>
            <pair>
              <locale country="US" lang="en" variant=""/>
              <value><![CDATA[=#"urn:appian:translation-string:v1:1ef8ea71-d1f4-4e54-909c-ab2083f30c0b"]]></value>
            </pair>
          </string-map>
        </process-name>
        <deadline>
          <enabled>false</enabled>
          <type>0</type>
          <units>0</units>
          <rex/>
          <aex/>
        </deadline>
        <pm-notification-settings>
          <custom-settings>true</custom-settings>
          <notify-initiator>false</notify-initiator>
          <notify-owner>false</notify-owner>
          <usersandgroups>
            <people>
              <type>4096</type>
              <stringId><![CDATA[_e-0000ed87-210d-8000-9b3b-01075c01075c_6565]]></stringId>
            </people>
          </usersandgroups>
          <recipients-exp/>
        </pm-notification-settings>
        <cleanup-action>2</cleanup-action>
        <auto-archive-delay>7</auto-archive-delay>
        <auto-delete-delay>3</auto-delete-delay>
        <timeZoneId><![CDATA[Europe/Brussels]]></timeZoneId>
        <useProcessInitiatorTimeZone>true</useProcessInitiatorTimeZone>
      </meta>
      <pvs>
        <pv name="event">
          <a:value xmlns:n1="urn:com:appian:recordtype:datatype"
            xsi:nil="true" xsi:type="n1:fa952da3-a305-45ce-924b-89ca2dab3222"/>
          <parameter>false</parameter>
          <required>false</required>
          <hidden>false</hidden>
        </pv>
        <pv name="eventHistory">
          <a:value xmlns:n1="urn:com:appian:recordtype:datatype"
            xsi:nil="true" xsi:type="n1:19d38ef9-1b48-4045-ad3a-9bd7be992dcb"/>
          <parameter>false</parameter>
          <required>false</required>
          <hidden>false</hidden>
        </pv>
        <pv name="eventId">
          <a:value xmlns="" xsi:type="xsd:int">0</a:value>
          <parameter>true</parameter>
          <required>false</required>
          <hidden>false</hidden>
        </pv>
        <pv name="eventOpinion">
          <a:value xmlns:n1="urn:com:appian:recordtype:datatype"
            xsi:nil="true" xsi:type="n1:d20e13d7-6450-4ab5-8eb8-31b00904e791"/>
          <parameter>true</parameter>
          <required>false</required>
          <hidden>false</hidden>
        </pv>
      </pvs>
      <nodes>
        <node uuid="0000ee0c-e41d-8000-270c-7f0000014e7a">
          <guiId>0</guiId>
          <owner/>
          <icon id="50"/>
          <picon id="0"/>
          <fname>
            <string-map>
              <pair>
                <locale country="" lang="de" variant=""/>
                <value><![CDATA[Start Node]]></value>
              </pair>
              <pair>
                <locale country="US" lang="en" variant=""/>
                <value><![CDATA[Start Node]]></value>
              </pair>
            </string-map>
          </fname>
          <x>112</x>
          <y>112</y>
          <display>
            <string-map>
              <pair>
                <locale country="" lang="de" variant=""/>
                <value><![CDATA[Start Node]]></value>
              </pair>
              <pair>
                <locale country="US" lang="en" variant=""/>
                <value><![CDATA[Start Node]]></value>
              </pair>
            </string-map>
          </display>
          <desc>
            <string-map>
              <pair>
                <locale country="" lang="de" variant=""/>
                <value/>
              </pair>
              <pair>
                <locale country="US" lang="en" variant=""/>
                <value/>
              </pair>
            </string-map>
          </desc>
          <notify>false</notify>
          <confirmation-url/>
          <lane>0</lane>
          <overrideLaneAssignment>false</overrideLaneAssignment>
          <ac>
            <local-id>core.0</local-id>
            <name><![CDATA[Start Node]]></name>
            <acps/>
            <custom-params/>
            <output-exprs/>
            <requires-user-interaction>true</requires-user-interaction>
            <run-as>
              <performer id="0"/>
            </run-as>
            <form-map/>
            <helper-class/>
          </ac>
          <multiple-instance/>
          <escalations/>
          <connections>
            <connection>
              <guiId>1</guiId>
              <to>2</to>
              <toObjectType>ap.gui.Node</toObjectType>
              <fromAnchor/>
              <toAnchor/>
              <showArrowhead>true</showArrowhead>
              <flowLabel/>
              <label>
                <fontColor>#000000</fontColor>
                <fontFamily>Appian Open Sans, Sans-Serif</fontFamily>
                <fontSize>12</fontSize>
                <bold>true</bold>
                <italics>false</italics>
                <underline>false</underline>
              </label>
              <associations/>
              <chained>false</chained>
              <overridesAssignment>true</overridesAssignment>
              <synchronizeData>false</synchronizeData>
            </connection>
          </connections>
          <associations/>
          <target-completion>5.0</target-completion>
          <target-lag>1.0</target-lag>
          <attachments/>
          <notes/>
          <lingering>false</lingering>
          <on-create-ignore-if-active>false</on-create-ignore-if-active>
          <on-create-delete-previous-active>false</on-create-delete-previous-active>
          <on-complete-delete-previous-completed>false</on-complete-delete-previous-completed>
          <pre-triggers/>
          <post-triggers/>
          <event-producers/>
          <exception-flow/>
          <label>
            <fontColor>#000000</fontColor>
            <fontFamily>Appian Open Sans, Sans-Serif</fontFamily>
            <fontSize>12</fontSize>
            <bold>false</bold>
            <italics>false</italics>
            <underline>false</underline>
          </label>
          <deadline>
            <enabled>false</enabled>
            <type>0</type>
            <units>0</units>
            <rex/>
            <aex/>
          </deadline>
          <allowsBack>false</allowsBack>
          <refreshDefaultValues>false</refreshDefaultValues>
          <on-complete-keep-form-data>false</on-complete-keep-form-data>
          <skipNotification>false</skipNotification>
        </node>
        <node uuid="0001ee0c-e41d-8000-270c-7f0000014e7a">
          <guiId>1</guiId>
          <owner/>
          <icon id="51"/>
          <picon id="0"/>
          <fname>
            <string-map>
              <pair>
                <locale country="" lang="de" variant=""/>
                <value><![CDATA[End Node]]></value>
              </pair>
              <pair>
                <locale country="US" lang="en" variant=""/>
                <value><![CDATA[End Node]]></value>
              </pair>
            </string-map>
          </fname>
          <x>952</x>
          <y>112</y>
          <display>
            <string-map>
              <pair>
                <locale country="" lang="de" variant=""/>
                <value><![CDATA[End Node]]></value>
              </pair>
              <pair>
                <locale country="US" lang="en" variant=""/>
                <value><![CDATA[End Node]]></value>
              </pair>
            </string-map>
          </display>
          <desc>
            <string-map>
              <pair>
                <locale country="" lang="de" variant=""/>
                <value/>
              </pair>
              <pair>
                <locale country="US" lang="en" variant=""/>
                <value/>
              </pair>
            </string-map>
          </desc>
          <notify>false</notify>
          <confirmation-url/>
          <lane>0</lane>
          <overrideLaneAssignment>false</overrideLaneAssignment>
          <ac>
            <local-id>core.1</local-id>
            <name><![CDATA[End Node]]></name>
            <acps>
              <acp name="pmID">
                <a:value xsi:nil="true" xsi:type="a:ProcessModel"/>
                <a:local-id>0</a:local-id>
                <a:expr/>
                <a:required>0</a:required>
                <a:editable>0</a:editable>
                <a:assign-to-pv/>
                <a:input-to-activity-class>true</a:input-to-activity-class>
                <a:hidden-from-designer>false</a:hidden-from-designer>
                <a:generated>false</a:generated>
                <a:enumeration/>
                <a:customDisplayReference/>
              </acp>
              <acp name="inMap">
                <a:value xsi:nil="true" xsi:type="a:Bean?list"/>
                <a:local-id>1</a:local-id>
                <a:expr/>
                <a:required>0</a:required>
                <a:editable>1</a:editable>
                <a:assign-to-pv/>
                <a:input-to-activity-class>true</a:input-to-activity-class>
                <a:hidden-from-designer>false</a:hidden-from-designer>
                <a:generated>false</a:generated>
                <a:enumeration/>
                <a:customDisplayReference/>
              </acp>
              <acp name="procInheritsPriority">
                <a:value xmlns="" xsi:type="xsd:int">1</a:value>
                <a:local-id>5</a:local-id>
                <a:expr/>
                <a:required>0</a:required>
                <a:editable>1</a:editable>
                <a:assign-to-pv/>
                <a:input-to-activity-class>false</a:input-to-activity-class>
                <a:hidden-from-designer>false</a:hidden-from-designer>
                <a:generated>false</a:generated>
                <a:enumeration/>
                <a:customDisplayReference/>
              </acp>
              <acp name="pmUUID">
                <a:value xsi:nil="true" xsi:type="xsd:string"/>
                <a:local-id>6</a:local-id>
                <a:expr/>
                <a:required>0</a:required>
                <a:editable>1</a:editable>
                <a:assign-to-pv/>
                <a:input-to-activity-class>true</a:input-to-activity-class>
                <a:hidden-from-designer>false</a:hidden-from-designer>
                <a:generated>false</a:generated>
                <a:enumeration/>
                <a:customDisplayReference/>
              </acp>
              <acp name="isAsynchronous">
                <a:value xmlns="" xsi:type="xsd:boolean">true</a:value>
                <a:local-id>7</a:local-id>
                <a:expr/>
                <a:required>1</a:required>
                <a:editable>0</a:editable>
                <a:assign-to-pv/>
                <a:input-to-activity-class>true</a:input-to-activity-class>
                <a:hidden-from-designer>true</a:hidden-from-designer>
                <a:generated>false</a:generated>
                <a:enumeration/>
                <a:customDisplayReference/>
              </acp>
              <acp name="isTransparent">
                <a:value xmlns="" xsi:type="xsd:boolean">true</a:value>
                <a:local-id>14</a:local-id>
                <a:expr/>
                <a:required>1</a:required>
                <a:editable>1</a:editable>
                <a:assign-to-pv/>
                <a:input-to-activity-class>true</a:input-to-activity-class>
                <a:hidden-from-designer>true</a:hidden-from-designer>
                <a:generated>false</a:generated>
                <a:enumeration/>
                <a:customDisplayReference/>
              </acp>
              <acp name="inheritSecurity">
                <a:value xmlns="" xsi:type="xsd:boolean">false</a:value>
                <a:local-id>15</a:local-id>
                <a:expr/>
                <a:required>1</a:required>
                <a:editable>1</a:editable>
                <a:assign-to-pv/>
                <a:input-to-activity-class>true</a:input-to-activity-class>
                <a:hidden-from-designer>true</a:hidden-from-designer>
                <a:generated>false</a:generated>
                <a:enumeration/>
                <a:customDisplayReference/>
              </acp>
            </acps>
            <custom-params/>
            <output-exprs/>
            <requires-user-interaction>true</requires-user-interaction>
            <run-as>
              <performer id="0"/>
            </run-as>
            <form-map/>
            <helper-class/>
          </ac>
          <multiple-instance/>
          <escalations/>
          <connections/>
          <associations/>
          <target-completion>5.0</target-completion>
          <target-lag>1.0</target-lag>
          <attachments/>
          <notes/>
          <lingering>false</lingering>
          <on-create-ignore-if-active>false</on-create-ignore-if-active>
          <on-create-delete-previous-active>false</on-create-delete-previous-active>
          <on-complete-delete-previous-completed>false</on-complete-delete-previous-completed>
          <pre-triggers/>
          <post-triggers/>
          <event-producers/>
          <exception-flow/>
          <label>
            <fontColor>#000000</fontColor>
            <fontFamily>Appian Open Sans, Sans-Serif</fontFamily>
            <fontSize>12</fontSize>
            <bold>false</bold>
            <italics>false</italics>
            <underline>false</underline>
          </label>
          <deadline>
            <enabled>false</enabled>
            <type>0</type>
            <units>0</units>
            <rex/>
            <aex/>
          </deadline>
          <allowsBack>false</allowsBack>
          <refreshDefaultValues>false</refreshDefaultValues>
          <on-complete-keep-form-data>false</on-complete-keep-form-data>
          <skipNotification>false</skipNotification>
        </node>
        <node uuid="0002ee0c-ec48-8000-2710-7f0000014e7a">
          <guiId>3</guiId>
          <owner/>
          <icon id="155"/>
          <picon id="155"/>
          <fname>
            <string-map>
              <pair>
                <locale country="" lang="de" variant=""/>
                <value/>
              </pair>
              <pair>
                <locale country="US" lang="en" variant=""/>
                <value><![CDATA[PS EVENT OPINION PS EVENT HISTORY]]></value>
              </pair>
            </string-map>
          </fname>
          <x>532</x>
          <y>112</y>
          <display>
            <string-map>
              <pair>
                <locale country="" lang="de" variant=""/>
                <value/>
              </pair>
              <pair>
                <locale country="US" lang="en" variant=""/>
                <value><![CDATA[PS EVENT OPINION PS EVENT HISTORY]]></value>
              </pair>
            </string-map>
          </display>
          <desc>
            <string-map>
              <pair>
                <locale country="" lang="de" variant=""/>
                <value/>
              </pair>
              <pair>
                <locale country="US" lang="en" variant=""/>
                <value/>
              </pair>
            </string-map>
          </desc>
          <notify>false</notify>
          <confirmation-url/>
          <lane>0</lane>
          <overrideLaneAssignment>false</overrideLaneAssignment>
          <ac>
            <local-id>internal3.write_records_to_source_23r3</local-id>
            <name><![CDATA[Write Records and Related Records]]></name>
            <acps>
              <acp name="Records">
                <a:value xsi:nil="true" xsi:type="a:Variant?list"/>
                <a:local-id>records</a:local-id>
                <a:expr><![CDATA[={pv!eventHistory, pv!eventOpinion}]]></a:expr>
                <a:required>1</a:required>
                <a:editable>1</a:editable>
                <a:assign-to-pv/>
                <a:input-to-activity-class>true</a:input-to-activity-class>
                <a:hidden-from-designer>true</a:hidden-from-designer>
                <a:generated>false</a:generated>
                <a:enumeration/>
                <a:customDisplayReference/>
              </acp>
              <acp name="PauseOnError">
                <a:value xmlns="" xsi:type="xsd:boolean">true</a:value>
                <a:local-id>pauseonerror</a:local-id>
                <a:expr/>
                <a:required>0</a:required>
                <a:editable>1</a:editable>
                <a:assign-to-pv/>
                <a:input-to-activity-class>true</a:input-to-activity-class>
                <a:hidden-from-designer>false</a:hidden-from-designer>
                <a:generated>false</a:generated>
                <a:enumeration/>
                <a:customDisplayReference/>
              </acp>
              <acp name="Version">
                <a:value xmlns="" xsi:type="xsd:int">6</a:value>
                <a:local-id>version</a:local-id>
                <a:expr/>
                <a:required>1</a:required>
                <a:editable>0</a:editable>
                <a:assign-to-pv/>
                <a:input-to-activity-class>true</a:input-to-activity-class>
                <a:hidden-from-designer>true</a:hidden-from-designer>
                <a:generated>false</a:generated>
                <a:enumeration/>
                <a:customDisplayReference/>
              </acp>
              <acp name="RecordType">
                <a:value xsi:nil="true" xsi:type="a:RecordType2"/>
                <a:local-id>recordtype</a:local-id>
                <a:expr><![CDATA[={#"urn:appian:record-type:v1:19d38ef9-1b48-4045-ad3a-9bd7be992dcb", #"urn:appian:record-type:v1:d20e13d7-6450-4ab5-8eb8-31b00904e791"}]]></a:expr>
                <a:required>0</a:required>
                <a:editable>1</a:editable>
                <a:assign-to-pv/>
                <a:input-to-activity-class>true</a:input-to-activity-class>
                <a:hidden-from-designer>true</a:hidden-from-designer>
                <a:generated>false</a:generated>
                <a:enumeration/>
                <a:customDisplayReference/>
              </acp>
              <acp name="CaptureEvents">
                <a:value xmlns="" xsi:type="xsd:boolean">false</a:value>
                <a:local-id>captureevents</a:local-id>
                <a:expr/>
                <a:required>1</a:required>
                <a:editable>1</a:editable>
                <a:assign-to-pv/>
                <a:input-to-activity-class>true</a:input-to-activity-class>
                <a:hidden-from-designer>true</a:hidden-from-designer>
                <a:generated>false</a:generated>
                <a:enumeration/>
                <a:customDisplayReference/>
              </acp>
              <acp name="RecordsUpdated">
                <a:value xsi:nil="true" xsi:type="a:Variant?list"/>
                <a:local-id>recordsupdated</a:local-id>
                <a:expr/>
                <a:required>0</a:required>
                <a:editable>1</a:editable>
                <a:assign-to-pv/>
                <a:input-to-activity-class>false</a:input-to-activity-class>
                <a:hidden-from-designer>false</a:hidden-from-designer>
                <a:generated>false</a:generated>
                <a:enumeration/>
                <a:customDisplayReference/>
              </acp>
              <acp name="ErrorOccurred">
                <a:value xsi:nil="true" xsi:type="xsd:boolean"/>
                <a:local-id>erroroccurred</a:local-id>
                <a:expr/>
                <a:required>0</a:required>
                <a:editable>1</a:editable>
                <a:assign-to-pv/>
                <a:input-to-activity-class>false</a:input-to-activity-class>
                <a:hidden-from-designer>false</a:hidden-from-designer>
                <a:generated>false</a:generated>
                <a:enumeration/>
                <a:customDisplayReference/>
              </acp>
              <acp name="Error">
                <a:value xsi:nil="true" xsi:type="xsd:string"/>
                <a:local-id>errors</a:local-id>
                <a:expr/>
                <a:required>0</a:required>
                <a:editable>1</a:editable>
                <a:assign-to-pv/>
                <a:input-to-activity-class>false</a:input-to-activity-class>
                <a:hidden-from-designer>false</a:hidden-from-designer>
                <a:generated>false</a:generated>
                <a:enumeration/>
                <a:customDisplayReference/>
              </acp>
              <acp name="RecordEvents_ReferencedFieldsMetadata">
                <a:value xmlns="" xsi:type="xsd:string">{}</a:value>
                <a:local-id/>
                <a:expr/>
                <a:required>0</a:required>
                <a:editable>1</a:editable>
                <a:assign-to-pv/>
                <a:input-to-activity-class>true</a:input-to-activity-class>
                <a:hidden-from-designer>true</a:hidden-from-designer>
                <a:generated>false</a:generated>
                <a:enumeration/>
                <a:customDisplayReference/>
              </acp>
            </acps>
            <custom-params/>
            <output-exprs/>
            <requires-user-interaction>true</requires-user-interaction>
            <run-as>
              <performer id="0"/>
            </run-as>
            <form-map>
              <pair>
                <locale country="" lang="de" variant=""/>
                <form-config>
                  <form>
                    <type>3</type>
                    <enabled>false</enabled>
                    <dynamic-form>
                      <form-elements/>
                    </dynamic-form>
                    <uiExpressionForm>
                      <expression><![CDATA[=/*41707069616E-GEN-DEBUG*/=a!formLayout(
  buttons: a!buttonLayout(
    primaryButtons: {
      a!buttonWidgetSubmit(
        label: "OK",
        style: "PRIMARY"
      )
    }
  ))]]></expression>
                    </uiExpressionForm>
                    <hiddenSections>16</hiddenSections>
                  </form>
                </form-config>
              </pair>
              <pair>
                <locale country="US" lang="en" variant=""/>
                <form-config>
                  <form>
                    <type>3</type>
                    <enabled>true</enabled>
                    <dynamic-form>
                      <form-elements/>
                    </dynamic-form>
                    <uiExpressionForm>
                      <expression><![CDATA[=/*41707069616E-GEN-DEBUG*/=a!formLayout(
  buttons: a!buttonLayout(
    primaryButtons: {
      a!buttonWidgetSubmit(
        label: "OK",
        style: "PRIMARY"
      )
    }
  ))]]></expression>
                    </uiExpressionForm>
                    <hiddenSections>16</hiddenSections>
                  </form>
                </form-config>
              </pair>
            </form-map>
            <helper-class/>
          </ac>
          <multiple-instance/>
          <escalations/>
          <connections>
            <connection>
              <guiId>2</guiId>
              <to>4</to>
              <toObjectType>ap.gui.Node</toObjectType>
              <fromAnchor/>
              <toAnchor/>
              <showArrowhead>true</showArrowhead>
              <flowLabel/>
              <label>
                <fontColor>#000000</fontColor>
                <fontFamily>Appian Open Sans, Sans-Serif</fontFamily>
                <fontSize>12</fontSize>
                <bold>false</bold>
                <italics>false</italics>
                <underline>false</underline>
              </label>
              <associations/>
              <chained>false</chained>
              <overridesAssignment>true</overridesAssignment>
              <synchronizeData>false</synchronizeData>
            </connection>
          </connections>
          <associations/>
          <target-completion>5.0</target-completion>
          <target-lag>1.0</target-lag>
          <attachments/>
          <notes/>
          <lingering>false</lingering>
          <on-create-ignore-if-active>false</on-create-ignore-if-active>
          <on-create-delete-previous-active>false</on-create-delete-previous-active>
          <on-complete-delete-previous-completed>false</on-complete-delete-previous-completed>
          <pre-triggers/>
          <post-triggers/>
          <event-producers/>
          <exception-flow/>
          <label>
            <fontColor>#000000</fontColor>
            <fontFamily>Appian Open Sans, Sans-Serif</fontFamily>
            <fontSize>12</fontSize>
            <bold>false</bold>
            <italics>false</italics>
            <underline>false</underline>
          </label>
          <deadline>
            <enabled>false</enabled>
            <type>0</type>
            <units>0</units>
            <rex/>
            <aex/>
          </deadline>
          <allowsBack>false</allowsBack>
          <refreshDefaultValues>false</refreshDefaultValues>
          <on-complete-keep-form-data>false</on-complete-keep-form-data>
          <skipNotification>false</skipNotification>
        </node>
        <node uuid="0003ee0c-ec48-8000-2710-7f0000014e7a">
          <guiId>6</guiId>
          <owner/>
          <icon id="68"/>
          <picon id="69"/>
          <fname>
            <string-map>
              <pair>
                <locale country="" lang="de" variant=""/>
                <value/>
              </pair>
              <pair>
                <locale country="US" lang="en" variant=""/>
                <value><![CDATA[Generate Event History]]></value>
              </pair>
            </string-map>
          </fname>
          <x>364</x>
          <y>112</y>
          <display>
            <string-map>
              <pair>
                <locale country="" lang="de" variant=""/>
                <value/>
              </pair>
              <pair>
                <locale country="US" lang="en" variant=""/>
                <value><![CDATA[Generate Event History]]></value>
              </pair>
            </string-map>
          </display>
          <desc>
            <string-map>
              <pair>
                <locale country="" lang="de" variant=""/>
                <value/>
              </pair>
              <pair>
                <locale country="US" lang="en" variant=""/>
                <value/>
              </pair>
            </string-map>
          </desc>
          <notify>false</notify>
          <confirmation-url/>
          <lane>0</lane>
          <overrideLaneAssignment>false</overrideLaneAssignment>
          <ac>
            <local-id>internal.16</local-id>
            <name><![CDATA[Unattended Multiple Questions]]></name>
            <acps/>
            <custom-params/>
            <output-exprs>
              <el typeFlag="0"><![CDATA[eventHistory:/*eventHistory*/
#"urn:appian:record-type:v1:19d38ef9-1b48-4045-ad3a-9bd7be992dcb"(
  #"urn:appian:record-field:v1:19d38ef9-1b48-4045-ad3a-9bd7be992dcb/4a99e364-d147-44c1-8f9e-3368886ea29c": pv!eventId,
  #"urn:appian:record-field:v1:19d38ef9-1b48-4045-ad3a-9bd7be992dcb/b8a5f0fc-fd84-4032-9a72-92964a957d9c": #"_a-0000ee09-79c9-8000-9bf0-011c48011c48_1476745"[2], /*update*/
  #"urn:appian:record-field:v1:19d38ef9-1b48-4045-ad3a-9bd7be992dcb/0f50d3b6-39a2-48fb-81e1-64f1962c9611": pv!eventOpinion[#"urn:appian:record-field:v1:d20e13d7-6450-4ab5-8eb8-31b00904e791/80d59003-45f5-4439-ba3b-56108d2077a6"],
  #"urn:appian:record-field:v1:19d38ef9-1b48-4045-ad3a-9bd7be992dcb/70c872e0-cad1-4383-8968-281ed7e31720": 1,
  #"urn:appian:record-field:v1:19d38ef9-1b48-4045-ad3a-9bd7be992dcb/293bc4ec-ec50-4019-bba7-81ccaaff7d5b": pv!eventOpinion[#"urn:appian:record-field:v1:d20e13d7-6450-4ab5-8eb8-31b00904e791/b816fde2-3f17-4fae-984d-c99216d6a968"] & " hinzugefügt",
  #"urn:appian:record-field:v1:19d38ef9-1b48-4045-ad3a-9bd7be992dcb/7f3aa1ca-cc5b-4d8f-ba65-5a7d59705c49": now()
)]]></el>
            </output-exprs>
            <requires-user-interaction>true</requires-user-interaction>
            <run-as>
              <performer id="0"/>
            </run-as>
            <form-map/>
            <helper-class/>
          </ac>
          <multiple-instance/>
          <escalations/>
          <connections>
            <connection>
              <guiId>8</guiId>
              <to>3</to>
              <toObjectType>ap.gui.Node</toObjectType>
              <fromAnchor/>
              <toAnchor/>
              <showArrowhead>true</showArrowhead>
              <flowLabel/>
              <label>
                <fontColor>#000000</fontColor>
                <fontFamily>Appian Open Sans, Sans-Serif</fontFamily>
                <fontSize>12</fontSize>
                <bold>false</bold>
                <italics>false</italics>
                <underline>false</underline>
              </label>
              <associations/>
              <chained>false</chained>
              <overridesAssignment>true</overridesAssignment>
              <synchronizeData>false</synchronizeData>
            </connection>
          </connections>
          <associations/>
          <target-completion>5.0</target-completion>
          <target-lag>1.0</target-lag>
          <attachments/>
          <notes/>
          <lingering>false</lingering>
          <on-create-ignore-if-active>false</on-create-ignore-if-active>
          <on-create-delete-previous-active>false</on-create-delete-previous-active>
          <on-complete-delete-previous-completed>false</on-complete-delete-previous-completed>
          <pre-triggers/>
          <post-triggers/>
          <event-producers/>
          <exception-flow/>
          <label>
            <fontColor>#000000</fontColor>
            <fontFamily>Appian Open Sans, Sans-Serif</fontFamily>
            <fontSize>12</fontSize>
            <bold>false</bold>
            <italics>false</italics>
            <underline>false</underline>
          </label>
          <deadline>
            <enabled>false</enabled>
            <type>0</type>
            <units>0</units>
            <rex/>
            <aex/>
          </deadline>
          <allowsBack>false</allowsBack>
          <refreshDefaultValues>false</refreshDefaultValues>
          <on-complete-keep-form-data>false</on-complete-keep-form-data>
          <skipNotification>false</skipNotification>
        </node>
        <node uuid="0002ee3c-5e6e-8000-2b12-7f0000014e7a">
          <guiId>5</guiId>
          <owner/>
          <icon id="155"/>
          <picon id="155"/>
          <fname>
            <string-map>
              <pair>
                <locale country="" lang="de" variant=""/>
                <value/>
              </pair>
              <pair>
                <locale country="US" lang="en" variant=""/>
                <value><![CDATA[Update Status PS EVENT]]></value>
              </pair>
            </string-map>
          </fname>
          <x>840</x>
          <y>112</y>
          <display>
            <string-map>
              <pair>
                <locale country="" lang="de" variant=""/>
                <value/>
              </pair>
              <pair>
                <locale country="US" lang="en" variant=""/>
                <value><![CDATA[Update Status PS EVENT]]></value>
              </pair>
            </string-map>
          </display>
          <desc>
            <string-map>
              <pair>
                <locale country="" lang="de" variant=""/>
                <value/>
              </pair>
              <pair>
                <locale country="US" lang="en" variant=""/>
                <value/>
              </pair>
            </string-map>
          </desc>
          <notify>false</notify>
          <confirmation-url/>
          <lane>0</lane>
          <overrideLaneAssignment>false</overrideLaneAssignment>
          <ac>
            <local-id>internal3.write_records_to_source_23r3</local-id>
            <name><![CDATA[Write Records and Related Records]]></name>
            <acps>
              <acp name="Records">
                <a:value xsi:nil="true" xsi:type="a:Variant?list"/>
                <a:local-id>records</a:local-id>
                <a:expr><![CDATA[={pv!event}]]></a:expr>
                <a:required>1</a:required>
                <a:editable>1</a:editable>
                <a:assign-to-pv/>
                <a:input-to-activity-class>true</a:input-to-activity-class>
                <a:hidden-from-designer>true</a:hidden-from-designer>
                <a:generated>false</a:generated>
                <a:enumeration/>
                <a:customDisplayReference/>
              </acp>
              <acp name="PauseOnError">
                <a:value xmlns="" xsi:type="xsd:boolean">true</a:value>
                <a:local-id>pauseonerror</a:local-id>
                <a:expr/>
                <a:required>0</a:required>
                <a:editable>1</a:editable>
                <a:assign-to-pv/>
                <a:input-to-activity-class>true</a:input-to-activity-class>
                <a:hidden-from-designer>false</a:hidden-from-designer>
                <a:generated>false</a:generated>
                <a:enumeration/>
                <a:customDisplayReference/>
              </acp>
              <acp name="Version">
                <a:value xmlns="" xsi:type="xsd:int">6</a:value>
                <a:local-id>version</a:local-id>
                <a:expr/>
                <a:required>1</a:required>
                <a:editable>0</a:editable>
                <a:assign-to-pv/>
                <a:input-to-activity-class>true</a:input-to-activity-class>
                <a:hidden-from-designer>true</a:hidden-from-designer>
                <a:generated>false</a:generated>
                <a:enumeration/>
                <a:customDisplayReference/>
              </acp>
              <acp name="RecordType">
                <a:value xsi:nil="true" xsi:type="a:RecordType2"/>
                <a:local-id>recordtype</a:local-id>
                <a:expr><![CDATA[={#"urn:appian:record-type:v1:fa952da3-a305-45ce-924b-89ca2dab3222"}]]></a:expr>
                <a:required>0</a:required>
                <a:editable>1</a:editable>
                <a:assign-to-pv/>
                <a:input-to-activity-class>true</a:input-to-activity-class>
                <a:hidden-from-designer>true</a:hidden-from-designer>
                <a:generated>false</a:generated>
                <a:enumeration/>
                <a:customDisplayReference/>
              </acp>
              <acp name="CaptureEvents">
                <a:value xmlns="" xsi:type="xsd:boolean">true</a:value>
                <a:local-id>captureevents</a:local-id>
                <a:expr/>
                <a:required>1</a:required>
                <a:editable>1</a:editable>
                <a:assign-to-pv/>
                <a:input-to-activity-class>true</a:input-to-activity-class>
                <a:hidden-from-designer>true</a:hidden-from-designer>
                <a:generated>false</a:generated>
                <a:enumeration/>
                <a:customDisplayReference/>
              </acp>
              <acp name="RecordsUpdated">
                <a:value xsi:nil="true" xsi:type="a:Variant?list"/>
                <a:local-id>recordsupdated</a:local-id>
                <a:expr/>
                <a:required>0</a:required>
                <a:editable>1</a:editable>
                <a:assign-to-pv/>
                <a:input-to-activity-class>false</a:input-to-activity-class>
                <a:hidden-from-designer>false</a:hidden-from-designer>
                <a:generated>false</a:generated>
                <a:enumeration/>
                <a:customDisplayReference/>
              </acp>
              <acp name="ErrorOccurred">
                <a:value xsi:nil="true" xsi:type="xsd:boolean"/>
                <a:local-id>erroroccurred</a:local-id>
                <a:expr/>
                <a:required>0</a:required>
                <a:editable>1</a:editable>
                <a:assign-to-pv/>
                <a:input-to-activity-class>false</a:input-to-activity-class>
                <a:hidden-from-designer>false</a:hidden-from-designer>
                <a:generated>false</a:generated>
                <a:enumeration/>
                <a:customDisplayReference/>
              </acp>
              <acp name="Error">
                <a:value xsi:nil="true" xsi:type="xsd:string"/>
                <a:local-id>errors</a:local-id>
                <a:expr/>
                <a:required>0</a:required>
                <a:editable>1</a:editable>
                <a:assign-to-pv/>
                <a:input-to-activity-class>false</a:input-to-activity-class>
                <a:hidden-from-designer>false</a:hidden-from-designer>
                <a:generated>false</a:generated>
                <a:enumeration/>
                <a:customDisplayReference/>
              </acp>
              <acp name="RecordEvents_ReferencedFieldsMetadata">
                <a:value xmlns="" xsi:type="xsd:string">{"urn:appian:record-field:v1:19d38ef9-1b48-4045-ad3a-9bd7be992dcb/b8a5f0fc-fd84-4032-9a72-92964a957d9c":{"isUsed":true},"urn:appian:record-field:v1:19d38ef9-1b48-4045-ad3a-9bd7be992dcb/0f50d3b6-39a2-48fb-81e1-64f1962c9611":{"isUsed":true},"urn:appian:record-field:v1:19d38ef9-1b48-4045-ad3a-9bd7be992dcb/7f3aa1ca-cc5b-4d8f-ba65-5a7d59705c49":{"isUsed":true},"urn:appian:record-field:v1:19d38ef9-1b48-4045-ad3a-9bd7be992dcb/70c872e0-cad1-4383-8968-281ed7e31720":{"isUsed":true},"urn:appian:record-field:v1:19d38ef9-1b48-4045-ad3a-9bd7be992dcb/293bc4ec-ec50-4019-bba7-81ccaaff7d5b":{"isUsed":false}}</a:value>
                <a:local-id/>
                <a:expr/>
                <a:required>0</a:required>
                <a:editable>1</a:editable>
                <a:assign-to-pv/>
                <a:input-to-activity-class>true</a:input-to-activity-class>
                <a:hidden-from-designer>true</a:hidden-from-designer>
                <a:generated>false</a:generated>
                <a:enumeration/>
                <a:customDisplayReference/>
              </acp>
              <acp name="EventType_uuid_b8a5f0fc_fd84_4032_9a72_92964a957d9c">
                <a:value xmlns="" xsi:type="xsd:int">3</a:value>
                <a:local-id/>
                <a:expr/>
                <a:required>1</a:required>
                <a:editable>1</a:editable>
                <a:assign-to-pv/>
                <a:input-to-activity-class>true</a:input-to-activity-class>
                <a:hidden-from-designer>true</a:hidden-from-designer>
                <a:generated>false</a:generated>
                <a:enumeration/>
                <a:customDisplayReference/>
              </acp>
              <acp name="User_uuid_0f50d3b6_39a2_48fb_81e1_64f1962c9611">
                <a:value xsi:nil="true" xsi:type="a:User?list"/>
                <a:local-id/>
                <a:expr><![CDATA[pp!initiator]]></a:expr>
                <a:required>1</a:required>
                <a:editable>1</a:editable>
                <a:assign-to-pv/>
                <a:input-to-activity-class>true</a:input-to-activity-class>
                <a:hidden-from-designer>true</a:hidden-from-designer>
                <a:generated>false</a:generated>
                <a:enumeration/>
                <a:customDisplayReference/>
              </acp>
              <acp name="Timestamp_uuid_7f3aa1ca_cc5b_4d8f_ba65_5a7d59705c49">
                <a:value xsi:nil="true" xsi:type="a:Datetime?list"/>
                <a:local-id/>
                <a:expr><![CDATA[now()]]></a:expr>
                <a:required>1</a:required>
                <a:editable>1</a:editable>
                <a:assign-to-pv/>
                <a:input-to-activity-class>true</a:input-to-activity-class>
                <a:hidden-from-designer>true</a:hidden-from-designer>
                <a:generated>false</a:generated>
                <a:enumeration/>
                <a:customDisplayReference/>
              </acp>
              <acp name="AutomationType_uuid_70c872e0_cad1_4383_8968_281ed7e31720">
                <a:value xsi:nil="true" xsi:type="a:Integer?list"/>
                <a:local-id/>
                <a:expr><![CDATA[a!automationId("NONE")]]></a:expr>
                <a:required>1</a:required>
                <a:editable>1</a:editable>
                <a:assign-to-pv/>
                <a:input-to-activity-class>true</a:input-to-activity-class>
                <a:hidden-from-designer>true</a:hidden-from-designer>
                <a:generated>false</a:generated>
                <a:enumeration/>
                <a:customDisplayReference/>
              </acp>
              <acp name="comment_uuid_293bc4ec_ec50_4019_bba7_81ccaaff7d5b">
                <a:value xsi:nil="true" xsi:type="xsd:string"/>
                <a:local-id/>
                <a:expr/>
                <a:required>0</a:required>
                <a:editable>1</a:editable>
                <a:assign-to-pv/>
                <a:input-to-activity-class>true</a:input-to-activity-class>
                <a:hidden-from-designer>true</a:hidden-from-designer>
                <a:generated>false</a:generated>
                <a:enumeration/>
                <a:customDisplayReference/>
              </acp>
            </acps>
            <custom-params/>
            <output-exprs/>
            <requires-user-interaction>true</requires-user-interaction>
            <run-as>
              <performer id="0"/>
            </run-as>
            <form-map>
              <pair>
                <locale country="" lang="de" variant=""/>
                <form-config>
                  <form>
                    <type>3</type>
                    <enabled>false</enabled>
                    <dynamic-form>
                      <form-elements/>
                    </dynamic-form>
                    <uiExpressionForm>
                      <expression><![CDATA[=/*41707069616E-GEN-DEBUG*/=a!formLayout(
  buttons: a!buttonLayout(
    primaryButtons: {
      a!buttonWidgetSubmit(
        label: "OK",
        style: "PRIMARY"
      )
    }
  ))]]></expression>
                    </uiExpressionForm>
                    <hiddenSections>16</hiddenSections>
                  </form>
                </form-config>
              </pair>
              <pair>
                <locale country="US" lang="en" variant=""/>
                <form-config>
                  <form>
                    <type>3</type>
                    <enabled>true</enabled>
                    <dynamic-form>
                      <form-elements/>
                    </dynamic-form>
                    <uiExpressionForm>
                      <expression><![CDATA[=/*41707069616E-GEN-DEBUG*/=a!formLayout(
  buttons: a!buttonLayout(
    primaryButtons: {
      a!buttonWidgetSubmit(
        label: "OK",
        style: "PRIMARY"
      )
    }
  ))]]></expression>
                    </uiExpressionForm>
                    <hiddenSections>16</hiddenSections>
                  </form>
                </form-config>
              </pair>
            </form-map>
            <helper-class/>
          </ac>
          <multiple-instance/>
          <escalations/>
          <connections>
            <connection>
              <guiId>5</guiId>
              <to>1</to>
              <toObjectType>ap.gui.Node</toObjectType>
              <fromAnchor/>
              <toAnchor/>
              <showArrowhead>true</showArrowhead>
              <flowLabel/>
              <label>
                <fontColor>#000000</fontColor>
                <fontFamily>Appian Open Sans, Sans-Serif</fontFamily>
                <fontSize>12</fontSize>
                <bold>false</bold>
                <italics>false</italics>
                <underline>false</underline>
              </label>
              <associations/>
              <chained>false</chained>
              <overridesAssignment>true</overridesAssignment>
              <synchronizeData>false</synchronizeData>
            </connection>
          </connections>
          <associations/>
          <target-completion>5.0</target-completion>
          <target-lag>1.0</target-lag>
          <attachments/>
          <notes/>
          <lingering>false</lingering>
          <on-create-ignore-if-active>false</on-create-ignore-if-active>
          <on-create-delete-previous-active>false</on-create-delete-previous-active>
          <on-complete-delete-previous-completed>false</on-complete-delete-previous-completed>
          <pre-triggers/>
          <post-triggers/>
          <event-producers/>
          <exception-flow/>
          <label>
            <fontColor>#000000</fontColor>
            <fontFamily>Appian Open Sans, Sans-Serif</fontFamily>
            <fontSize>12</fontSize>
            <bold>false</bold>
            <italics>false</italics>
            <underline>false</underline>
          </label>
          <deadline>
            <enabled>false</enabled>
            <type>0</type>
            <units>0</units>
            <rex/>
            <aex/>
          </deadline>
          <allowsBack>false</allowsBack>
          <refreshDefaultValues>false</refreshDefaultValues>
          <on-complete-keep-form-data>false</on-complete-keep-form-data>
          <skipNotification>false</skipNotification>
        </node>
        <node uuid="0001ee3c-5e6e-8000-2b12-7f0000014e7a">
          <guiId>4</guiId>
          <owner/>
          <icon id="68"/>
          <picon id="69"/>
          <fname>
            <string-map>
              <pair>
                <locale country="" lang="de" variant=""/>
                <value/>
              </pair>
              <pair>
                <locale country="US" lang="en" variant=""/>
                <value><![CDATA[Event Status]]></value>
              </pair>
            </string-map>
          </fname>
          <x>672</x>
          <y>112</y>
          <display>
            <string-map>
              <pair>
                <locale country="" lang="de" variant=""/>
                <value/>
              </pair>
              <pair>
                <locale country="US" lang="en" variant=""/>
                <value><![CDATA[Event Status]]></value>
              </pair>
            </string-map>
          </display>
          <desc>
            <string-map>
              <pair>
                <locale country="" lang="de" variant=""/>
                <value/>
              </pair>
              <pair>
                <locale country="US" lang="en" variant=""/>
                <value/>
              </pair>
            </string-map>
          </desc>
          <notify>false</notify>
          <confirmation-url/>
          <lane>0</lane>
          <overrideLaneAssignment>false</overrideLaneAssignment>
          <ac>
            <local-id>internal.16</local-id>
            <name><![CDATA[Unattended Multiple Questions]]></name>
            <acps/>
            <custom-params/>
            <output-exprs>
              <el typeFlag="0"><![CDATA[event[#"urn:appian:record-field:v1:fa952da3-a305-45ce-924b-89ca2dab3222/d08885b1-046b-446d-9bc9-86441cb51aa1"]:/*Event Status = Stellungnahme(-n) (Zeugenaussagen und/oder Gutachten) wurden angefordert, sind aber (noch) nicht eingegangen..*/

#"_a-0000ee0e-a4b3-8000-9bf2-011c48011c48_1624662"]]></el>
            </output-exprs>
            <requires-user-interaction>true</requires-user-interaction>
            <run-as>
              <performer id="0"/>
            </run-as>
            <form-map/>
            <helper-class/>
          </ac>
          <multiple-instance/>
          <escalations/>
          <connections>
            <connection>
              <guiId>4</guiId>
              <to>5</to>
              <toObjectType>ap.gui.Node</toObjectType>
              <fromAnchor/>
              <toAnchor/>
              <showArrowhead>true</showArrowhead>
              <flowLabel/>
              <label>
                <fontColor>#000000</fontColor>
                <fontFamily>Appian Open Sans, Sans-Serif</fontFamily>
                <fontSize>12</fontSize>
                <bold>false</bold>
                <italics>false</italics>
                <underline>false</underline>
              </label>
              <associations/>
              <chained>false</chained>
              <overridesAssignment>true</overridesAssignment>
              <synchronizeData>false</synchronizeData>
            </connection>
          </connections>
          <associations/>
          <target-completion>5.0</target-completion>
          <target-lag>1.0</target-lag>
          <attachments/>
          <notes/>
          <lingering>false</lingering>
          <on-create-ignore-if-active>false</on-create-ignore-if-active>
          <on-create-delete-previous-active>false</on-create-delete-previous-active>
          <on-complete-delete-previous-completed>false</on-complete-delete-previous-completed>
          <pre-triggers/>
          <post-triggers/>
          <event-producers/>
          <exception-flow/>
          <label>
            <fontColor>#000000</fontColor>
            <fontFamily>Appian Open Sans, Sans-Serif</fontFamily>
            <fontSize>12</fontSize>
            <bold>false</bold>
            <italics>false</italics>
            <underline>false</underline>
          </label>
          <deadline>
            <enabled>false</enabled>
            <type>0</type>
            <units>0</units>
            <rex/>
            <aex/>
          </deadline>
          <allowsBack>false</allowsBack>
          <refreshDefaultValues>false</refreshDefaultValues>
          <on-complete-keep-form-data>false</on-complete-keep-form-data>
          <skipNotification>false</skipNotification>
        </node>
        <node uuid="0001ee0c-ec48-8000-2710-7f0000014e7a">
          <guiId>2</guiId>
          <owner/>
          <icon id="21"/>
          <picon id="1"/>
          <fname>
            <string-map>
              <pair>
                <locale country="" lang="de" variant=""/>
                <value><![CDATA[Stellungnahme ausfüllen]]></value>
              </pair>
              <pair>
                <locale country="US" lang="en" variant=""/>
                <value><![CDATA[Fill Out Opinion]]></value>
              </pair>
            </string-map>
          </fname>
          <x>224</x>
          <y>112</y>
          <display>
            <string-map>
              <pair>
                <locale country="" lang="de" variant=""/>
                <value><![CDATA[=pv!eventOpinion[#"urn:appian:record-field:v1:d20e13d7-6450-4ab5-8eb8-31b00904e791/b816fde2-3f17-4fae-984d-c99216d6a968"] & " ausfüllen"]]></value>
              </pair>
              <pair>
                <locale country="US" lang="en" variant=""/>
                <value><![CDATA[="Fill out Opinion"]]></value>
              </pair>
            </string-map>
          </display>
          <desc>
            <string-map>
              <pair>
                <locale country="" lang="de" variant=""/>
                <value/>
              </pair>
              <pair>
                <locale country="US" lang="en" variant=""/>
                <value/>
              </pair>
            </string-map>
          </desc>
          <notify>false</notify>
          <confirmation-url/>
          <lane>0</lane>
          <overrideLaneAssignment>false</overrideLaneAssignment>
          <assignments>
            <assignee>
              <type>29</type>
              <privilege>3</privilege>
              <value>
                <ac>
                  <local-id>assignee-pool.102</local-id>
                  <name><![CDATA[Assign To Expression]]></name>
                  <acps>
                    <acp name="expression">
                      <a:value xsi:nil="true" xsi:type="a:UserOrGroup?list"/>
                      <a:local-id>0</a:local-id>
                      <a:expr><![CDATA[=pv!eventOpinion[#"urn:appian:record-field:v1:d20e13d7-6450-4ab5-8eb8-31b00904e791/80d59003-45f5-4439-ba3b-56108d2077a6"]]]></a:expr>
                      <a:required>0</a:required>
                      <a:editable>1</a:editable>
                      <a:assign-to-pv/>
                      <a:input-to-activity-class>true</a:input-to-activity-class>
                      <a:hidden-from-designer>false</a:hidden-from-designer>
                      <a:generated>false</a:generated>
                      <a:enumeration/>
                      <a:customDisplayReference/>
                    </acp>
                    <acp name="outUsers">
                      <a:value xsi:nil="true" xsi:type="a:User?list"/>
                      <a:local-id>1</a:local-id>
                      <a:expr/>
                      <a:required>0</a:required>
                      <a:editable>1</a:editable>
                      <a:assign-to-pv/>
                      <a:input-to-activity-class>false</a:input-to-activity-class>
                      <a:hidden-from-designer>false</a:hidden-from-designer>
                      <a:generated>false</a:generated>
                      <a:enumeration/>
                      <a:customDisplayReference/>
                    </acp>
                    <acp name="outGroups">
                      <a:value xsi:nil="true" xsi:type="a:Group?list"/>
                      <a:local-id>2</a:local-id>
                      <a:expr/>
                      <a:required>0</a:required>
                      <a:editable>1</a:editable>
                      <a:assign-to-pv/>
                      <a:input-to-activity-class>false</a:input-to-activity-class>
                      <a:hidden-from-designer>false</a:hidden-from-designer>
                      <a:generated>false</a:generated>
                      <a:enumeration/>
                      <a:customDisplayReference/>
                    </acp>
                  </acps>
                  <custom-params/>
                  <output-exprs/>
                  <requires-user-interaction>true</requires-user-interaction>
                  <run-as>
                    <performer id="0"/>
                  </run-as>
                  <helper-class/>
                </ac>
              </value>
            </assignee>
            <assignment-function/>
            <position>0</position>
            <accept-mode>1</accept-mode>
          </assignments>
          <ac>
            <local-id>internal.17</local-id>
            <name><![CDATA[User Input Task]]></name>
            <acps/>
            <custom-params>
              <acp name="eventId">
                <a:value xsi:nil="true" xsi:type="xsd:int"/>
                <a:local-id/>
                <a:expr><![CDATA[=pv!eventId]]></a:expr>
                <a:required>0</a:required>
                <a:editable>1</a:editable>
                <a:assign-to-pv/>
                <a:input-to-activity-class>true</a:input-to-activity-class>
                <a:hidden-from-designer>false</a:hidden-from-designer>
                <a:generated>false</a:generated>
                <a:enumeration/>
                <a:customDisplayReference/>
              </acp>
              <acp name="eventOpinion">
                <a:value xmlns:n1="urn:com:appian:recordtype:datatype"
                  xsi:nil="true" xsi:type="n1:d20e13d7-6450-4ab5-8eb8-31b00904e791"/>
                <a:local-id/>
                <a:expr><![CDATA[=pv!eventOpinion]]></a:expr>
                <a:required>0</a:required>
                <a:editable>1</a:editable>
                <a:assign-to-pv><![CDATA[eventOpinion]]></a:assign-to-pv>
                <a:input-to-activity-class>true</a:input-to-activity-class>
                <a:hidden-from-designer>false</a:hidden-from-designer>
                <a:generated>false</a:generated>
                <a:enumeration/>
                <a:customDisplayReference/>
              </acp>
            </custom-params>
            <output-exprs/>
            <requires-user-interaction>false</requires-user-interaction>
            <run-as>
              <performer id="0"/>
            </run-as>
            <form-map>
              <pair>
                <locale country="" lang="de" variant=""/>
                <form-config>
                  <form>
                    <type>3</type>
                    <enabled>false</enabled>
                    <dynamic-form>
                      <form-elements/>
                    </dynamic-form>
                    <uiExpressionForm>
                      <expression><![CDATA[/*41707069616E-GEN-DEBUG*/=#"SYSTEM_SYSRULES_formLayout_v2"(
  buttons: #"SYSTEM_SYSRULES_ButtonLayout"(
    primaryButtons: {
      #"SYSTEM_SYSRULES_ButtonWidgetSubmit"(
        label: "OK",
        style: "PRIMARY"
      )
    }
  ))]]></expression>
                    </uiExpressionForm>
                    <hiddenSections>16</hiddenSections>
                  </form>
                </form-config>
              </pair>
              <pair>
                <locale country="US" lang="en" variant=""/>
                <form-config>
                  <form>
                    <type>3</type>
                    <enabled>true</enabled>
                    <dynamic-form>
                      <form-elements/>
                    </dynamic-form>
                    <uiExpressionForm>
                      <expression><![CDATA[/*41707069616E-GEN*/#"_a-0000ee09-79c9-8000-9bf0-011c48011c48_1477213"(
	eventId: ac!eventId,
	eventOpinion: ac!eventOpinion
)]]></expression>
                    </uiExpressionForm>
                    <interfaceInformation>
                      <name>PS_F_FillOutEventOpinion</name>
                      <uuid>_a-0000ee09-79c9-8000-9bf0-011c48011c48_1477213</uuid>
                      <ruleInputs>
                        <ruleInput>
                          <name>eventId</name>
                          <typeQName>{http://www.appian.com/ae/types/2009}Integer</typeQName>
                          <value><![CDATA[ac!eventId]]></value>
                        </ruleInput>
                        <ruleInput>
                          <name>eventOpinion</name>
                          <typeQName>{urn:com:appian:recordtype:datatype}d20e13d7-6450-4ab5-8eb8-31b00904e791</typeQName>
                          <value><![CDATA[ac!eventOpinion]]></value>
                        </ruleInput>
                      </ruleInputs>
                    </interfaceInformation>
                    <hiddenSections>16</hiddenSections>
                  </form>
                </form-config>
              </pair>
            </form-map>
            <helper-class/>
          </ac>
          <multiple-instance/>
          <escalations/>
          <connections>
            <connection>
              <guiId>7</guiId>
              <to>6</to>
              <toObjectType>ap.gui.Node</toObjectType>
              <fromAnchor/>
              <toAnchor/>
              <showArrowhead>true</showArrowhead>
              <flowLabel/>
              <label>
                <fontColor>#000000</fontColor>
                <fontFamily>Appian Open Sans, Sans-Serif</fontFamily>
                <fontSize>12</fontSize>
                <bold>false</bold>
                <italics>false</italics>
                <underline>false</underline>
              </label>
              <associations/>
              <chained>false</chained>
              <overridesAssignment>true</overridesAssignment>
              <synchronizeData>false</synchronizeData>
            </connection>
          </connections>
          <associations/>
          <target-completion>5.0</target-completion>
          <target-lag>1.0</target-lag>
          <attachments/>
          <notes/>
          <lingering>false</lingering>
          <on-create-ignore-if-active>false</on-create-ignore-if-active>
          <on-create-delete-previous-active>false</on-create-delete-previous-active>
          <on-complete-delete-previous-completed>false</on-complete-delete-previous-completed>
          <pre-triggers/>
          <post-triggers/>
          <event-producers/>
          <exception-flow/>
          <label>
            <fontColor>#000000</fontColor>
            <fontFamily>Appian Open Sans, Sans-Serif</fontFamily>
            <fontSize>12</fontSize>
            <bold>false</bold>
            <italics>false</italics>
            <underline>false</underline>
          </label>
          <deadline>
            <enabled>true</enabled>
            <type>0</type>
            <units>2</units>
            <rex><![CDATA[=3]]></rex>
            <aex/>
          </deadline>
          <allowsBack>false</allowsBack>
          <refreshDefaultValues>false</refreshDefaultValues>
          <on-complete-keep-form-data>false</on-complete-keep-form-data>
          <skipNotification>false</skipNotification>
        </node>
      </nodes>
      <annotations/>
      <lanes>
        <lane>
          <laneLabel><![CDATA[Statement Assignee]]></laneLabel>
          <dimension>224</dimension>
          <color>#07ab57</color>
          <isVertical>false</isVertical>
          <isLaneAssignment>false</isLaneAssignment>
          <assignments>
            <assignment-function/>
            <position>0</position>
            <accept-mode>1</accept-mode>
          </assignments>
          <unattended>0</unattended>
          <runAs>0</runAs>
          <label>
            <fontColor>#000000</fontColor>
            <fontFamily>Appian Open Sans, Sans-Serif</fontFamily>
            <fontSize>12</fontSize>
            <bold>true</bold>
            <italics>false</italics>
            <underline>false</underline>
          </label>
        </lane>
      </lanes>
      <attachments/>
      <notes/>
      <priority id="1"/>
      <form-map>
        <pair>
          <locale country="" lang="de" variant=""/>
          <form-config>
            <form>
              <type>3</type>
              <enabled>false</enabled>
              <dynamic-form>
                <form-elements/>
              </dynamic-form>
              <hiddenSections>16</hiddenSections>
            </form>
          </form-config>
        </pair>
        <pair>
          <locale country="US" lang="en" variant=""/>
          <form-config>
            <form>
              <type>3</type>
              <enabled>true</enabled>
              <dynamic-form>
                <form-elements/>
              </dynamic-form>
              <hiddenSections>16</hiddenSections>
            </form>
          </form-config>
        </pair>
      </form-map>
      <isPublic>false</isPublic>
      <isEPEx>false</isEPEx>
    </pm>
  </process_model_port>
  <isPublished>true</isPublished>
  <history>
    <historyInfo versionUuid="0001ee28-9ab4-8000-29e3-7f0000014e7a"/>
    <historyInfo versionUuid="0001ee3c-5ec4-8000-2b13-7f0000014e7a"/>
    <historyInfo versionUuid="0001ee4d-47e0-8000-8a0f-109188109188"/>
  </history>
</processModelHaul>
