<?xml version="1.0" encoding="UTF-8"?>
<translationStringHaul xmlns:a="http://www.appian.com/ae/types/2009">
  <versionUuid>70f9c1b8-03e3-4a97-8c38-b75c3c2b6170</versionUuid>
  <translationString a:uuid="3c2f1b79-f08c-47dd-a565-3fe566a9f5be">
    <a:translationSetUuid>5f1fccd2-d309-46dc-a451-abf6d078df5a</a:translationSetUuid>
    <a:description/>
    <a:translatorNotes/>
    <translationTexts>
      <translatedText>
        <a:translationLocale>
          <a:localeLanguageTag>en-US</a:localeLanguageTag>
        </a:translationLocale>
        <a:translatedText>Inmates</a:translatedText>
      </translatedText>
      <translatedText>
        <a:translationLocale>
          <a:localeLanguageTag>de</a:localeLanguageTag>
        </a:translationLocale>
        <a:translatedText>Gefangene</a:translatedText>
      </translatedText>
    </translationTexts>
    <translationStringVariables/>
  </translationString>
  <history>
    <historyInfo versionUuid="7f026a36-9d73-478d-9e7a-bd4a892fd09e"/>
    <historyInfo versionUuid="70f9c1b8-03e3-4a97-8c38-b75c3c2b6170"/>
  </history>
</translationStringHaul>
