<?xml version="1.0" encoding="UTF-8"?>
<translationStringHaul xmlns:a="http://www.appian.com/ae/types/2009">
  <versionUuid>fe69c5d7-2805-440e-b9e7-5c7e5194600f</versionUuid>
  <translationString a:uuid="4017e339-6f79-454b-a5b2-6da958d6c059">
    <a:translationSetUuid>5f1fccd2-d309-46dc-a451-abf6d078df5a</a:translationSetUuid>
    <a:description/>
    <a:translatorNotes/>
    <translationTexts>
      <translatedText>
        <a:translationLocale>
          <a:localeLanguageTag>en-US</a:localeLanguageTag>
        </a:translationLocale>
        <a:translatedText>Request</a:translatedText>
      </translatedText>
      <translatedText>
        <a:translationLocale>
          <a:localeLanguageTag>de</a:localeLanguageTag>
        </a:translationLocale>
        <a:translatedText>Antrag</a:translatedText>
      </translatedText>
    </translationTexts>
    <translationStringVariables/>
  </translationString>
  <history>
    <historyInfo versionUuid="fe69c5d7-2805-440e-b9e7-5c7e5194600f"/>
  </history>
</translationStringHaul>
