<?xml version="1.0" encoding="UTF-8"?>
<translationStringHaul xmlns:a="http://www.appian.com/ae/types/2009">
  <versionUuid>20ed6f38-6838-445a-9582-72ff4da8a0d4</versionUuid>
  <translationString a:uuid="82b78122-6de8-4402-a3a7-f251b4dd8211">
    <a:translationSetUuid>5f1fccd2-d309-46dc-a451-abf6d078df5a</a:translationSetUuid>
    <a:description/>
    <a:translatorNotes/>
    <translationTexts>
      <translatedText>
        <a:translationLocale>
          <a:localeLanguageTag>de</a:localeLanguageTag>
        </a:translationLocale>
        <a:translatedText>Der Antrag wird veraktet.</a:translatedText>
      </translatedText>
      <translatedText>
        <a:translationLocale>
          <a:localeLanguageTag>en-US</a:localeLanguageTag>
        </a:translationLocale>
        <a:translatedText>The request will be filed in the official record.</a:translatedText>
      </translatedText>
    </translationTexts>
    <translationStringVariables/>
  </translationString>
  <history>
    <historyInfo versionUuid="20ed6f38-6838-445a-9582-72ff4da8a0d4"/>
  </history>
</translationStringHaul>
