<?xml version="1.0" encoding="UTF-8"?>
<translationStringHaul xmlns:a="http://www.appian.com/ae/types/2009">
  <versionUuid>678cbee7-0f81-4f03-bceb-cb46e1558968</versionUuid>
  <translationString a:uuid="b123f98b-a4c2-488c-b744-a265d9aeaab9">
    <a:translationSetUuid>5f1fccd2-d309-46dc-a451-abf6d078df5a</a:translationSetUuid>
    <a:description/>
    <a:translatorNotes/>
    <translationTexts>
      <translatedText>
        <a:translationLocale>
          <a:localeLanguageTag>en-US</a:localeLanguageTag>
        </a:translationLocale>
        <a:translatedText>Sentence</a:translatedText>
      </translatedText>
      <translatedText>
        <a:translationLocale>
          <a:localeLanguageTag>de</a:localeLanguageTag>
        </a:translationLocale>
        <a:translatedText>Verurteilung</a:translatedText>
      </translatedText>
    </translationTexts>
    <translationStringVariables/>
  </translationString>
  <history>
    <historyInfo versionUuid="678cbee7-0f81-4f03-bceb-cb46e1558968"/>
  </history>
</translationStringHaul>
